[
    {
        "img": "/src/img/lc.svg",
        "alt": "Listeners Club",
        "title": "Listeners Club logo"
    },
    {
        "img": "/src/img/caribou-grove.svg",
        "alt": "Caribou Grove",
        "title": "Caribou Grove"
    },
    {
        "img": "/src/img/untitled.svg",
        "alt": ""
    },
    {
        "img": "/src/img/martimes-caravan-circle.svg"
    },
    {
        "img": "/src/img/going-east-going-fast.svg"
    },
    {
        "img": "/src/img/whitecap.svg",
        "alt": "",
        "title": "Whitecap Coffee identity"
    },
    {
        "img": "/src/img/library-lover-wb.svg",
        "alt": "South Central Regional Library Lover",
        "link": "/journal/2023/our-library/"
    },
    {
        "img": "/src/img/rw_thumb.jpg",
        "alt": "",
        "title": "Roundnet Winkler identity"
    },
    {
        "img": "/src/img/whitecap-wordmark.svg",
        "title": "Whitecap Coffee logo"
    },
    {
        "img": "/src/img/ted-charity-open-logo.svg",
        "title": "Triple E Developments Charity Open"
    },
    {
        "img": "/src/img/tcfp_thumb.svg",
        "alt": "TC Forest Products",
        "title": "TC Forest Products"
    },
    {
        "img": "/src/img/tripps_thumb.svg",
        "alt": "Tripp’s Tree Care logo",
        "title": "Tripp’s Tree Care logo"
    },
    {
        "img": "/src/img/whatevertown.svg",
        "title": "Whatevertown"
    },
    {
        "img": "/src/img/cascade-island.svg",
        "alt": ""
    },
    {
        "img": "/src/img/cascade-island-acnh.jpg",
        "alt": "screenshot of a custom designed flag in Animal Crossing: New Horizons",
        "title": "Cascade Island flag in Animal Crossing: New Horizons"
    },
    {
        "img": "/src/img/roundnet-winkler_pins.svg",
        "alt": ""
    },
    {
        "img": "/src/img/whatevertown_pillars.jpg",
        "alt": "",
        "title": "Whatevertown"
    },
    {
        "img": "/src/img/misc-logo-globe.svg"
    },
    {
        "img": "/src/img/whitecap_shirt_drinking-coffee.jpg",
        "alt": "Tripp’s Tree Care"
    },
    {
        "img": "/src/img/reignite.svg",
        "alt": ""
    },
    {
        "img": "/src/img/misc-logo-hive.svg",
        "alt": ""
    },
    {
        "img": "/src/img/works-end.svg",
        "alt": "",
        "title": "Works End"
    },
    {
        "img": "/src/img/misc-logo-coffee.svg"
    },
    {
        "img": "/src/img/whitecap_tea.jpg",
        "title": "Whitecap Coffee menu"
    },
    {
        "img": "/src/img/ccl.png",
        "title": "Country Club Lane"
    },
    {
        "img": "/src/img/mtg.svg",
        "title": "Mend the Gap"
    },
    {
        "img": "/src/img/misc-logo-forest.svg"
    },
    {
        "img": "/src/img/whitecap_whit3cap.jpg"
    },
    {
        "img": "/src/img/misc-logo-manitoba.svg"
    },
    {
        "img": "/src/img/untitled.png"
    },
    { 
        "img": "/src/img/aesthletico.png"
    },
    {
        "img": "/src/img/alliance.svg"
    },
    {
        "img": "/src/img/zodiacs-red-on-black.svg",
        "title": "Zodiacs"
    }
    
]